{"POP 100":{"Enginetransmission":{"oil_section_1":{"oil_names":["Petronox 10W-50","Petronox 10W-50","Petronox 20W-50"],"oil_properties":["Change interval: Normal","- Change 4000 km/ 12 months","- Capacity 0,9 liter (Dry fill)","- Capacity 0,7 liter (Service fill)"]},"oil_section_2":{"oil_names":["Petronox 10W-50","Petronox 10W-50","Petronox 20W-50"],"oil_properties":["Change interval: Initial service","- Change 1000 km","- Capacity 0,9 liter (Dry fill)","- Capacity 0,7 liter (Service fill)"]}}},"POP 110i":{"Enginetransmission":{"oil_section_1":{"oil_names":["Petronox 10W-30","Petronox 10W-40","Petronox 10W-40","Petronox 10W-30","Petronox 10W-40","Petronox 10W-40","Petronox 10W-40","Petronox 10W-40","Petronox 10W-40"],"oil_properties":["Change interval: Normal","- Change 6000 km","- Capacity 1 liter (Dry fill)","- Capacity 0,8 liter (Service fill)"]},"oil_section_2":{"oil_names":["Petronox 10W-30","Petronox 10W-40","Petronox 10W-40","Petronox 10W-30","Petronox 10W-40","Petronox 10W-40","Petronox 10W-40","Petronox 10W-40","Petronox 10W-40"],"oil_properties":["Change interval: Initial service","- Change 1000 km","- Capacity 1 liter (Dry fill)","- Capacity 0,8 liter (Service fill)"]}}}}