{"Actyon Actyon Sports":["Actyon Actyon Sports 20 CRDi 2WD","Actyon Actyon Sports 20 CRDi 4WD","Actyon Actyon Sports M230 2WD","Actyon Actyon Sports M230 4WD","Actyon Actyon Sports XDi200 2WD","Actyon Actyon Sports XDi200 2WD DPF","Actyon Actyon Sports XDi200 4WD","Actyon Actyon Sports XDi200 4WD DPF","Actyon Actyon Sports e-XDi200 2WD","Actyon Actyon Sports e-XDi200 4WD","Actyon Actyon Sports e-XDi220 2WD","Actyon Actyon Sports e-XDi220 4WD"],"Chairman H":["Chairman H 23 16V CM400","Chairman H 28 24V CM500","Chairman H 32 24V CM600"],"Korando":["Korando 15 T-GDi","Korando 15 T-GDi 4WD","Korando 16 E-XDi","Korando 16 E-XDi 4WD","Korando 22 D","Korando 23 16V","Korando 23 D","Korando 25 D","Korando 29 D","Korando 29 TD 88 kW","Korando 29 TD 95 kW","Korando 32 24V"],"Korando C":["Korando C 20 2WD","Korando C 20 4WD","Korando C e-XDi200 2WD","Korando C e-XDi200 4WD","Korando C e-XDi220 2WD","Korando C e-XDi220 4WD"],"Korando E-motion":["Korando E-motion"],"Kyron":["Kyron M230 2WD","Kyron M230 4WD","Kyron M320 4WD","Kyron XDi200 2WD","Kyron XDi200 4WD","Kyron XDi200 XVT 2WD","Kyron XDi200 XVT 2WD DPF","Kyron XDi200 XVT 4WD","Kyron XDi200 XVT 4WD DPF","Kyron XDi270 2WD","Kyron XDi270 2WD DPF","Kyron XDi270 4WD","Kyron XDi270 4WD DPF"],"Musso":["Musso 23 16V","Musso 23 D","Musso 29 D","Musso 29 TD","Musso 32 24V"],"Musso Q200Q250":["Musso 20 e-XGDI AWD Q200","Musso 20 e-XGDI Q200","Musso 22 e-XDI AWD Q200","Musso 22 e-XDI Q200"],"Rexton":["Rexton 230","Rexton 270 XDi","Rexton 290 Td","Rexton 320","Rexton M320 4WD","Rexton RX200 4WD","Rexton RX200 4WD DPF","Rexton RX200 4WD Euro 5","Rexton RX270 2WD","Rexton RX270 2WD DPF","Rexton RX270 4WD","Rexton RX270 4WD DPF","Rexton RX270 XVT 2WD","Rexton RX270 XVT 2WD DPF","Rexton RX270 XVT 4WD","Rexton RX270 XVT 4WD DPF"],"Rexton W":["Rexton W RX200 e-XDi 2WD","Rexton W RX200 e-XDi 4WD","Rexton W RX220 e-XDi 2WD","Rexton W RX220 e-XDi 4WD"],"Rexton Y400Y450":["Rexton e-XDi220 2WD Y400","Rexton e-XDi220 2WD Y450","Rexton e-XDi220 4WD Y400","Rexton e-XDi220 4WD Y450"],"Rodius Stavic":["Rodius Stavic 270 XDi","Rodius Stavic 320","Rodius Turismo Stavic SV 320 2WD","Rodius Turismo Stavic SV 320 4WD","Rodius Turismo Stavic SV e-XDI200 2WD","Rodius Turismo Stavic SV e-XDi200 4WD","Rodius Turismo Stavic SV e-XDi220 2WD","Rodius Turismo Stavic SV e-XDi220 4WD"],"Tivoli":["Tivoli 12 T-GDi","Tivoli 15 T-GDi","Tivoli 15 T-GDi 4WD","Tivoli 16 E-XDi","Tivoli 16 e-XDi 4WD","Tivoli e-XDi160 2WD","Tivoli e-XDi160 4WD","Tivoli e-XGi160 2WD","Tivoli e-XGi160 4WD"],"Tivoli Grand":["Tivoli Grand 12 T-GDi","Tivoli Grand 15 T-GDi","Tivoli Grand 15 T-GDi 4WD"],"Torres":["Torres 15 T-GDi","Torres 15 T-GDi 4WD"],"XLV":["XLV 16 e-XDi 2WD","XLV 16 e-XDi 4WD","XLV 16 e-XGi 2WD","XLV 16 e-XGi 4WD"]}